vislab/__init__.py
vislab/vislab.py
vislab/static/asset-manifest.json
vislab/static/favicon.ico
vislab/static/index.html
vislab/static/logo192.png
vislab/static/logo512.png
vislab/static/manifest.json
vislab/static/robots.txt
vislab/static/css/main.51d5342d.css
vislab/static/css/main.51d5342d.css.map
vislab/static/js/main.02b1ccc7.js
vislab/static/js/main.02b1ccc7.js.LICENSE.txt
vislab/static/js/main.02b1ccc7.js.map
vislab-0.0.5.dist-info/METADATA
vislab-0.0.5.dist-info/WHEEL
vislab-0.0.5.dist-info/top_level.txt
vislab-0.0.5.dist-info/RECORD
