Metadata-Version: 2.1
Name: vislab
Version: 0.0.5
Summary: VisLab: A set of visualization tools for robotics and computer vision researchers.
Home-page: https://github.com/jianglongye/vislab
Author: Jianglong Ye
Author-email: jianglong.yeh@gmail.com
Project-URL: Bug Tracker, https://github.com/jianglongye/vislab/issues
Classifier: Programming Language :: Python :: 3
Classifier: License :: OSI Approved :: MIT License
Classifier: Operating System :: OS Independent
Requires-Python: >=3.6
Requires-Dist: flask
Requires-Dist: flask-cors
Requires-Dist: flask-socketio
Requires-Dist: simple-websocket
Requires-Dist: numpy
Requires-Dist: trimesh
